odoo/addons/marketing_crm_partner/README.rst
odoo/addons/marketing_crm_partner/__init__.py
odoo/addons/marketing_crm_partner/__manifest__.py
odoo/addons/marketing_crm_partner/i18n/am.po
odoo/addons/marketing_crm_partner/i18n/ar.po
odoo/addons/marketing_crm_partner/i18n/bg.po
odoo/addons/marketing_crm_partner/i18n/bs.po
odoo/addons/marketing_crm_partner/i18n/ca.po
odoo/addons/marketing_crm_partner/i18n/cs.po
odoo/addons/marketing_crm_partner/i18n/da.po
odoo/addons/marketing_crm_partner/i18n/de.po
odoo/addons/marketing_crm_partner/i18n/el_GR.po
odoo/addons/marketing_crm_partner/i18n/en_GB.po
odoo/addons/marketing_crm_partner/i18n/es.po
odoo/addons/marketing_crm_partner/i18n/es_AR.po
odoo/addons/marketing_crm_partner/i18n/es_CO.po
odoo/addons/marketing_crm_partner/i18n/es_CR.po
odoo/addons/marketing_crm_partner/i18n/es_DO.po
odoo/addons/marketing_crm_partner/i18n/es_EC.po
odoo/addons/marketing_crm_partner/i18n/es_MX.po
odoo/addons/marketing_crm_partner/i18n/es_PE.po
odoo/addons/marketing_crm_partner/i18n/es_VE.po
odoo/addons/marketing_crm_partner/i18n/et.po
odoo/addons/marketing_crm_partner/i18n/eu.po
odoo/addons/marketing_crm_partner/i18n/fi.po
odoo/addons/marketing_crm_partner/i18n/fr.po
odoo/addons/marketing_crm_partner/i18n/fr_CA.po
odoo/addons/marketing_crm_partner/i18n/fr_CH.po
odoo/addons/marketing_crm_partner/i18n/gl.po
odoo/addons/marketing_crm_partner/i18n/he.po
odoo/addons/marketing_crm_partner/i18n/hr.po
odoo/addons/marketing_crm_partner/i18n/hr_HR.po
odoo/addons/marketing_crm_partner/i18n/hu.po
odoo/addons/marketing_crm_partner/i18n/id.po
odoo/addons/marketing_crm_partner/i18n/it.po
odoo/addons/marketing_crm_partner/i18n/ja.po
odoo/addons/marketing_crm_partner/i18n/ko.po
odoo/addons/marketing_crm_partner/i18n/lt.po
odoo/addons/marketing_crm_partner/i18n/lv.po
odoo/addons/marketing_crm_partner/i18n/marketing_crm_partner.pot
odoo/addons/marketing_crm_partner/i18n/mk.po
odoo/addons/marketing_crm_partner/i18n/mn.po
odoo/addons/marketing_crm_partner/i18n/nb.po
odoo13_addon_marketing_crm_partner-13.0.1.0.2.dist-info/METADATA
odoo13_addon_marketing_crm_partner-13.0.1.0.2.dist-info/WHEEL
odoo13_addon_marketing_crm_partner-13.0.1.0.2.dist-info/top_level.txt
odoo13_addon_marketing_crm_partner-13.0.1.0.2.dist-info/RECORD
